sqlalchemy_crud/__init__.py
sqlalchemy_crud/crud.py
sqlalchemy_crud-0.2.2.dist-info/LICENSE
sqlalchemy_crud-0.2.2.dist-info/METADATA
sqlalchemy_crud-0.2.2.dist-info/WHEEL
sqlalchemy_crud-0.2.2.dist-info/RECORD
