Metadata-Version: 2.1
Name: sqlalchemy-crud
Version: 0.2.2
Summary: Basic C.R.U.D for SQLAlchemy models
Home-page: https://github.com/cblack34/sqlalchemy-crud
License: MIT
Author: Clayton Black
Requires-Python: >=3.8,<4.0
Classifier: License :: OSI Approved :: MIT License
Classifier: Programming Language :: Python :: 3
Classifier: Programming Language :: Python :: 3.8
Classifier: Programming Language :: Python :: 3.9
Classifier: Programming Language :: Python :: 3.10
Classifier: Programming Language :: Python :: 3.11
Requires-Dist: SQLAlchemy (>=1.3.19,<2.0.0)
Requires-Dist: py (>=1.11.0,<2.0.0)
Requires-Dist: toml (>=0.10.2,<0.11.0)
Project-URL: Bug Tracker, https://github.com/cblack34/sqlalchemy-crud/issues
Project-URL: Repository, https://github.com/cblack34/sqlalchemy-crud
